lightberry/__init__.py
lightberry-1.1.1.dist-info/METADATA
lightberry-1.1.1.dist-info/WHEEL
lightberry-1.1.1.dist-info/top_level.txt
lightberry-1.1.1.dist-info/RECORD
