Metadata-Version: 2.1
Name: lightberry
Version: 1.1.1
Summary: Lightberry Libraries
Home-page: https://www.samclark.me/
Author: Sam Clark
Author-email: slc2015@icloud.com
License: UNKNOWN
Platform: UNKNOWN
Classifier: Programming Language :: Python :: 3
Classifier: License :: OSI Approved :: MIT License
Classifier: Operating System :: OS Independent
Requires-Dist: paho-mqtt
Requires-Dist: pycryptodome
